{"nodes": [{"id": "caveman_skill_caveman", "label": "Caveman Mode", "file_type": "concept", "source_file": ".agents/skills/caveman/SKILL.md", "source_location": null, "source_url": null, "captured_at": null, "author": null, "contributor": null, "rationale": "Ultra-compressed communication mode that cuts token usage ~75% by dropping filler, articles, and pleasantries while keeping full technical accuracy."}], "edges": [{"source": "caveman_skill_caveman", "target": "grill_me_skill_grill_me", "relation": "semantically_similar_to", "confidence": "INFERRED", "confidence_score": 0.75, "source_file": ".agents/skills/caveman/SKILL.md", "source_location": null, "weight": 1.0}], "hyperedges": []}